awessome/__init__.py
awessome/awessome_aggregator.py
awessome/awessome_builder.py
awessome/awessome_scorer.py
awessome/awessome_similarity.py
awessome/labmt.txt
awessome/vader.txt
awessome-0.0.14.dist-info/LICENSE.txt
awessome-0.0.14.dist-info/METADATA
awessome-0.0.14.dist-info/WHEEL
awessome-0.0.14.dist-info/top_level.txt
awessome-0.0.14.dist-info/RECORD
