Metadata-Version: 2.1
Name: awessome
Version: 0.0.14
Summary: awessome
Home-page: https://github.com/cumulative-revelations/awessome
Author: Amal Htait and Leif Azzopardi
Author-email: amal.htait@strath.ac.uk, leif.azzopardi@strath.ac.uk
License: MIT
Keywords: awessome,sentiment,analysis,opinion,mining,nlp,text,data,text analysis,opinion analysis,sentiment analysis,text mining,twitter sentiment,opinion mining,social media,twitter,social,media
Platform: any
Classifier: Development Status :: 4 - Beta
Classifier: Intended Audience :: Science/Research
Classifier: License :: OSI Approved :: MIT License
Classifier: Natural Language :: English
Classifier: Programming Language :: Python :: 3.5
Classifier: Topic :: Scientific/Engineering :: Artificial Intelligence
Classifier: Topic :: Scientific/Engineering :: Information Analysis
Classifier: Topic :: Text Processing :: Linguistic
Classifier: Topic :: Text Processing :: General
Requires-Dist: certifi (==2020.6.20)
Requires-Dist: chardet (==3.0.4)
Requires-Dist: click (==7.1.2)
Requires-Dist: dataclasses (==0.6)
Requires-Dist: filelock (==3.0.12)
Requires-Dist: future (==0.18.2)
Requires-Dist: idna (==2.10)
Requires-Dist: joblib (==0.17.0)
Requires-Dist: nltk (==3.5)
Requires-Dist: numpy (==1.19.2)
Requires-Dist: packaging (==20.4)
Requires-Dist: pyparsing (==2.4.7)
Requires-Dist: regex (==2020.10.23)
Requires-Dist: requests (==2.24.0)
Requires-Dist: sacremoses (==0.0.43)
Requires-Dist: scikit-learn (==0.23.2)
Requires-Dist: scipy (==1.5.3)
Requires-Dist: sentence-transformers (==0.3.8)
Requires-Dist: sentencepiece (==0.1.94)
Requires-Dist: six (==1.15.0)
Requires-Dist: threadpoolctl (==2.1.0)
Requires-Dist: tokenizers (==0.8.1rc2)
Requires-Dist: torch (==1.7.0)
Requires-Dist: tqdm (==4.51.0)
Requires-Dist: transformers (==3.3.1)
Requires-Dist: typing-extensions (==3.7.4.3)
Requires-Dist: urllib3 (==1.25.11)
